caspio/__init__.py
caspio-0.1.dist-info/LICENSE
caspio-0.1.dist-info/METADATA
caspio-0.1.dist-info/WHEEL
caspio-0.1.dist-info/top_level.txt
caspio-0.1.dist-info/RECORD
