Metadata-Version: 2.1
Name: caspio
Version: 0.1
Summary: lib for caspio
Home-page: UNKNOWN
Author: Arseniy
Author-email: senyaza@mail.ru
License: UNKNOWN
Platform: UNKNOWN
Classifier: Programming Language :: Python :: 3
Classifier: License :: OSI Approved :: MIT License
Classifier: Operating System :: OS Independent
License-File: LICENSE
